simple_smtp_sender-0.3.1.dist-info/METADATA
simple_smtp_sender-0.3.1.dist-info/WHEEL
simple_smtp_sender/__init__.py
simple_smtp_sender/__init__.pyi
simple_smtp_sender/py.typed
simple_smtp_sender/simple_smtp_sender.abi3.so
simple_smtp_sender-0.3.1.dist-info/RECORD
