Metadata-Version: 2.4
Name: simple_smtp_sender
Version: 0.3.1
Classifier: Programming Language :: Rust
Classifier: Programming Language :: Python :: Implementation :: CPython
Classifier: Programming Language :: Python :: Implementation :: PyPy
Summary: A Simple SMTP Email sender crate with the support of sync or async sending. Can be called from Python. Powered by PyO3.
Author: Guangyu He <fredhgy2010@gmail.com>
Author-email: Guangyu He <fredhgy2010@gmail.com>
License: MIT
Requires-Python: >=3.10
Project-URL: Source Code, https://github.com/guangyuhe/simple_smtp_sender
